pytrain_api/__init__.py
pytrain_api/_version.py
pytrain_api/endpoints.py
pytrain_api/make_api_service.py
pytrain_api/pytrain_api.py
pytrain_api/pytrain_component.py
pytrain_api/pytrain_info.py
pytrain_api/response_models.py
pytrain_api/static/apple-touch-icon.png
pytrain_api/static/favicon.ico
pytrain_api/static/pytrain_api.bash.template
pytrain_api/static/pytrain_api.service.template
pytrain_ogr_api-1.6.11.dist-info/licenses/AUTHORS
pytrain_ogr_api-1.6.11.dist-info/licenses/LICENSE
pytrain_ogr_api-1.6.11.dist-info/METADATA
pytrain_ogr_api-1.6.11.dist-info/WHEEL
pytrain_ogr_api-1.6.11.dist-info/entry_points.txt
pytrain_ogr_api-1.6.11.dist-info/top_level.txt
pytrain_ogr_api-1.6.11.dist-info/RECORD
