Metadata-Version: 2.4
Name: pytrain-ogr-api
Version: 1.6.11
Summary: Restful API to control Lionel TMCC/Legacy engines, switches, and accesseries from a Raspberry Pi
Author-email: Dave Swindell <pytraininfo@gmail.com>
License:                    GNU LESSER GENERAL PUBLIC LICENSE
Project-URL: Homepage, https://github.com/cdswindell/PyTrainApi
Project-URL: Source, https://github.com/cdswindell/PyTrainApi
Project-URL: Issues, https://github.com/cdswindell/PyTrainApi/issues
Keywords: alexa,api,rest,pytrain,legacy,lionel,model railroad,o-gauge,raspberry pi,tmcc,trains
Classifier: Development Status :: 4 - Beta
Classifier: Environment :: Console
Classifier: Intended Audience :: Developers
Classifier: Intended Audience :: Other Audience
Classifier: License :: OSI Approved :: GNU Lesser General Public License v3 (LGPLv3)
Classifier: Natural Language :: English
Classifier: Operating System :: POSIX :: Linux
Classifier: Operating System :: MacOS :: MacOS X
Classifier: Programming Language :: Python :: 3
Classifier: Programming Language :: Python :: 3.11
Classifier: Programming Language :: Python :: 3.12
Classifier: Programming Language :: Python :: 3.13
Requires-Python: >=3.11
License-File: LICENSE
License-File: AUTHORS
Requires-Dist: pytrain-ogr>=1.6.11
Requires-Dist: fastapi>=0.128.0
Requires-Dist: fastapi-utils>=0.8.0
Requires-Dist: pyjwt>=2.11.0
Requires-Dist: python-dotenv>=1.1.1
Requires-Dist: python_multipart>=0.0.20
Requires-Dist: range-key-dict>=1.1.0
Requires-Dist: setuptools>=80.9.0
Requires-Dist: setuptools_scm>=9.2.2
Requires-Dist: typing-inspect>=0.9.0
Requires-Dist: uvicorn>=0.40.0
Requires-Dist: zeroconf>=0.148.0
Dynamic: license-file
